MANIFEST.in
README.md
setup.py
docker_registry_statistics/__init__.py
docker_registry_statistics/__main__.py
docker_registry_statistics/blob_loader.py
docker_registry_statistics/image_storage.py
docker_registry_statistics/revision_storage.py
docker_registry_statistics/tag_storage.py
docker_registry_statistics/types.py
docker_registry_statistics/utils.py
docker_registry_statistics.egg-info/PKG-INFO
docker_registry_statistics.egg-info/SOURCES.txt
docker_registry_statistics.egg-info/dependency_links.txt
docker_registry_statistics.egg-info/entry_points.txt
docker_registry_statistics.egg-info/requires.txt
docker_registry_statistics.egg-info/top_level.txt
docker_registry_statistics/commands/__init__.py
docker_registry_statistics/commands/statistics.py
docker_registry_statistics/commands/untagged_images.py
docker_registry_statistics/commands/unused_blobs.py