Metadata-Version: 2.1
Name: docker-registry-statistics
Version: 0.1.0
Summary: Tool which will calculates disk usage statistics of docker registry
Home-page: https://github.com/pbabics/docker-registry-statistics/
Author: Peter Babics
Author-email: peter.ntx@gmail.com
License: UNKNOWN
Project-URL: Bug Reports, https://github.com/pbabics/docker-registry-statistics/issues
Project-URL: Source, https://github.com/pbabics/docker-registry-statistics/
Keywords: docker registry gitlab statistics
Platform: UNKNOWN
Classifier: Development Status :: 3 - Alpha
Classifier: Intended Audience :: Developers
Classifier: Topic :: System :: Monitoring
Classifier: License :: OSI Approved :: GNU General Public License v3 (GPLv3)
Classifier: Programming Language :: Python :: 3
Classifier: Programming Language :: Python :: 3.6
Classifier: Programming Language :: Python :: 3.7
